{
  "openapi": "3.0.1",
  "info": {
    "title": "AirlineCompanyAPI",
    "version": "1.0"
  },
  "paths": {
    "/v{version}/Flight/InsertFlight": {
      "post": {
        "tags": [
          "Flight"
        ],
        "parameters": [
          {
            "name": "version",
            "in": "path",
            "required": true,
            "schema": {
              "type": "string"
            }
          }
        ],
        "requestBody": {
          "content": {
            "application/json": {
              "schema": {
                "$ref": "#/components/schemas/FlightRequestDTO"
              }
            },
            "text/json": {
              "schema": {
                "$ref": "#/components/schemas/FlightRequestDTO"
              }
            },
            "application/*+json": {
              "schema": {
                "$ref": "#/components/schemas/FlightRequestDTO"
              }
            }
          }
        },
        "responses": {
          "200": {
            "description": "OK"
          }
        }
      }
    },
    "/v{version}/Flight/QueryFlights": {
      "get": {
        "tags": [
          "Flight"
        ],
        "parameters": [
          {
            "name": "from",
            "in": "query",
            "schema": {
              "type": "string"
            }
          },
          {
            "name": "to",
            "in": "query",
            "schema": {
              "type": "string"
            }
          },
          {
            "name": "date",
            "in": "query",
            "schema": {
              "type": "string"
            }
          },
          {
            "name": "pageNumber",
            "in": "query",
            "schema": {
              "type": "integer",
              "format": "int32",
              "default": 1
            }
          },
          {
            "name": "pageSize",
            "in": "query",
            "schema": {
              "type": "integer",
              "format": "int32",
              "default": 10
            }
          },
          {
            "name": "version",
            "in": "path",
            "required": true,
            "schema": {
              "type": "string"
            }
          }
        ],
        "responses": {
          "200": {
            "description": "OK"
          }
        }
      }
    },
    "/v{version}/Flight/ReportFlights": {
      "get": {
        "tags": [
          "Flight"
        ],
        "parameters": [
          {
            "name": "from",
            "in": "query",
            "schema": {
              "type": "string"
            }
          },
          {
            "name": "to",
            "in": "query",
            "schema": {
              "type": "string"
            }
          },
          {
            "name": "date",
            "in": "query",
            "schema": {
              "type": "string"
            }
          },
          {
            "name": "capacity",
            "in": "query",
            "schema": {
              "type": "integer",
              "format": "int32"
            }
          },
          {
            "name": "pageNumber",
            "in": "query",
            "schema": {
              "type": "integer",
              "format": "int32",
              "default": 1
            }
          },
          {
            "name": "pageSize",
            "in": "query",
            "schema": {
              "type": "integer",
              "format": "int32",
              "default": 10
            }
          },
          {
            "name": "version",
            "in": "path",
            "required": true,
            "schema": {
              "type": "string"
            }
          }
        ],
        "responses": {
          "200": {
            "description": "OK"
          }
        }
      }
    },
    "/api/Login/Login": {
      "post": {
        "tags": [
          "Login"
        ],
        "requestBody": {
          "content": {
            "application/json": {
              "schema": {
                "$ref": "#/components/schemas/UserLoginDTO"
              }
            },
            "text/json": {
              "schema": {
                "$ref": "#/components/schemas/UserLoginDTO"
              }
            },
            "application/*+json": {
              "schema": {
                "$ref": "#/components/schemas/UserLoginDTO"
              }
            }
          }
        },
        "responses": {
          "200": {
            "description": "OK"
          }
        }
      }
    },
    "/v{version}/Ticket/Book": {
      "post": {
        "tags": [
          "Ticket"
        ],
        "parameters": [
          {
            "name": "version",
            "in": "path",
            "required": true,
            "schema": {
              "type": "string"
            }
          }
        ],
        "requestBody": {
          "content": {
            "application/json": {
              "schema": {
                "$ref": "#/components/schemas/TicketRequestDTO"
              }
            },
            "text/json": {
              "schema": {
                "$ref": "#/components/schemas/TicketRequestDTO"
              }
            },
            "application/*+json": {
              "schema": {
                "$ref": "#/components/schemas/TicketRequestDTO"
              }
            }
          }
        },
        "responses": {
          "200": {
            "description": "OK"
          }
        }
      }
    },
    "/v{version}/Ticket/CheckIn": {
      "post": {
        "tags": [
          "Ticket"
        ],
        "parameters": [
          {
            "name": "version",
            "in": "path",
            "required": true,
            "schema": {
              "type": "string"
            }
          }
        ],
        "requestBody": {
          "content": {
            "application/json": {
              "schema": {
                "type": "integer",
                "format": "int32"
              }
            },
            "text/json": {
              "schema": {
                "type": "integer",
                "format": "int32"
              }
            },
            "application/*+json": {
              "schema": {
                "type": "integer",
                "format": "int32"
              }
            }
          }
        },
        "responses": {
          "200": {
            "description": "OK"
          }
        }
      }
    }
  },
  "components": {
    "schemas": {
      "FlightRequestDTO": {
        "required": [
          "availableDates",
          "capacity",
          "days",
          "from",
          "to"
        ],
        "type": "object",
        "properties": {
          "from": {
            "maxLength": 100,
            "minLength": 1,
            "type": "string"
          },
          "to": {
            "maxLength": 100,
            "minLength": 1,
            "type": "string"
          },
          "availableDates": {
            "minLength": 1,
            "type": "string"
          },
          "days": {
            "minLength": 1,
            "type": "string"
          },
          "capacity": {
            "maximum": 2147483647,
            "minimum": 1,
            "type": "integer",
            "format": "int32"
          }
        },
        "additionalProperties": false
      },
      "TicketRequestDTO": {
        "type": "object",
        "properties": {
          "flightId": {
            "type": "integer",
            "format": "int32"
          },
          "passengerFullName": {
            "type": "string",
            "nullable": true
          },
          "bookingDate": {
            "type": "string",
            "format": "date-time",
            "nullable": true
          }
        },
        "additionalProperties": false
      },
      "UserLoginDTO": {
        "type": "object",
        "properties": {
          "username": {
            "type": "string",
            "nullable": true
          },
          "password": {
            "type": "string",
            "nullable": true
          }
        },
        "additionalProperties": false
      }
    },
    "securitySchemes": {
      "Bearer": {
        "type": "apiKey",
        "description": "Enter 'Bearer' [space] and then your valid token. Example: 'Bearer abc123'",
        "name": "Authorization",
        "in": "header"
      }
    }
  },
  "security": [
    {
      "Bearer": [ ]
    }
  ]
}